ESPNN/SPNN.py
ESPNN/__init__.py
ESPNN/__main__.py
ESPNN/core.py
ESPNN/dataset.py
ESPNN/inference.py
ESPNN/run_Kinf.py
ESPNN/utils.py
ESPNN/data/__init__.py
ESPNN/data/formula_mapper.py
ESPNN/data/input/chemicalProperties.csv
ESPNN/data/input/ionization_energies_wiki.txt
ESPNN/data/preprocess/std_scaler.zip
ESPNN/data/weights/FOLD0_try0__00_en_ioen_0_bhe_corrected_trtestsplit_tuple_reduxdrop_nobias_yeslog_standard4all_dbscan2_mid_30_randomsplit_FORCEprojMASSall.pth
ESPNN/data/weights/FOLD1_try0__00_en_ioen_0_bhe_corrected_trtestsplit_tuple_reduxdrop_nobias_yeslog_standard4all_dbscan2_mid_30_randomsplit_FORCEprojMASSall.pth
ESPNN/data/weights/FOLD2_try0__00_en_ioen_0_bhe_corrected_trtestsplit_tuple_reduxdrop_nobias_yeslog_standard4all_dbscan2_mid_30_randomsplit_FORCEprojMASSall.pth
ESPNN/data/weights/FOLD3_try0__00_en_ioen_0_bhe_corrected_trtestsplit_tuple_reduxdrop_nobias_yeslog_standard4all_dbscan2_mid_30_randomsplit_FORCEprojMASSall.pth
ESPNN/data/weights/FOLD4_try0__00_en_ioen_0_bhe_corrected_trtestsplit_tuple_reduxdrop_nobias_yeslog_standard4all_dbscan2_mid_30_randomsplit_FORCEprojMASSall.pth
ESPNN-1.0.0.dist-info/LICENSE
ESPNN-1.0.0.dist-info/METADATA
ESPNN-1.0.0.dist-info/WHEEL
ESPNN-1.0.0.dist-info/top_level.txt
ESPNN-1.0.0.dist-info/RECORD
