Metadata-Version: 2.1
Name: ESPNN
Version: 1.0.0
Summary: Electronic Stopping Power Neural Network predictor
Home-page: https://github.com/ale-mendez/SPNN
Author: 
Author-email: felipebihaiek@gmail.com, alemdz.7@gmail.com
License: The GPLv3 License
Keywords: Stopping Power,Energy Loss,Atoms,Molecules,Ions,Machine Learning,Neural Network
Classifier: Development Status :: 4 - Beta
Classifier: Intended Audience :: Education
Classifier: Intended Audience :: Science/Research
Classifier: License :: OSI Approved :: GNU General Public License v3 (GPLv3)
Classifier: Operating System :: OS Independent
Classifier: Programming Language :: Python
Classifier: Programming Language :: Python :: 3.7
Classifier: Programming Language :: Python :: 3.8
Classifier: Programming Language :: Python :: 3.9
Classifier: Topic :: Scientific/Engineering
License-File: LICENSE
Requires-Dist: matplotlib (==3.5.2)
Requires-Dist: numpy (>=1.21.6)
Requires-Dist: pandas (>=1.3.5)
Requires-Dist: pyvalem (==2.5.7)
Requires-Dist: torch (==1.11.0)
Requires-Dist: scikit-learn (==0.24.2)
Requires-Dist: joblib (>=1.0.0)
